text_classification/__init__.py
text_classification/binary_classification.py
text_classification/image_classification.py
text_classification/multiple_classification.py
text_classification/text_classification.py
TextClassification-0.2.4.dist-info/METADATA
TextClassification-0.2.4.dist-info/WHEEL
TextClassification-0.2.4.dist-info/top_level.txt
TextClassification-0.2.4.dist-info/RECORD
