Metadata-Version: 2.1
Name: TextClassification
Version: 0.2.4
Summary: Create Text Classification Fine-Tunning Model
Home-page: https://github.com/falahgs/
Author: Falahgs.G.Saleih
Author-email: falahgs07@gmail.com
License: MIT
Keywords: transformers,datasets
Classifier: Programming Language :: Python :: 3
Classifier: License :: OSI Approved :: MIT License
Classifier: Operating System :: OS Independent
Requires-Python: >=3.6
Requires-Dist: transformers (==4.27.0)
Requires-Dist: datasets (==2.9)
Requires-Dist: evaluate
